speedtab/__init__.py
speedtab/client.py
speedtab/enums.py
speedtab/formats.py
speedtab-0.2.5.3.dist-info/WHEEL
speedtab-0.2.5.3.dist-info/METADATA
speedtab-0.2.5.3.dist-info/RECORD
