Metadata-Version: 2.1
Name: speedtab
Version: 0.2.5.3
Summary: Convenient wrapper for working with Google Spreadsheets
Home-page: https://github.com/BoggerSancho/SpeedTab-beta
License: MIT
Author: Bogdan Gergel
Author-email: bogger147@gmail.com
Requires-Python: >=3.7,<4.0
Classifier: License :: OSI Approved :: MIT License
Classifier: Programming Language :: Python :: 3
Classifier: Programming Language :: Python :: 3.10
Classifier: Programming Language :: Python :: 3.7
Classifier: Programming Language :: Python :: 3.8
Classifier: Programming Language :: Python :: 3.9
Requires-Dist: google-api-python-client (>=2.58.0,<3.0.0)
Requires-Dist: google-auth-httplib2 (>=0.1.0,<0.2.0)
Requires-Dist: google-auth-oauthlib (>=0.5.2,<0.6.0)
Project-URL: Repository, https://github.com/BoggerSancho/SpeedTab-beta
